{"m":"Na Jaane Kaun Aa Gaya","rd":"2026-03-06","premiere":false,"v":1,"src":"bfilmyapi","ec":"ET00486882","img":"https://assets-in.bmscdn.com/iedb/movies/images/mobile/thumbnail/large/na-jaane-kaun-aa-gaya-et00486882-1773675835.jpg","og":"https://assets-in.bmscdn.com/iedb/movies/images/mobile/listing/xxlarge/na-jaane-kaun-aa-gaya-et00486882-1773675835.jpg","d":"Na Jaane Kaun Aa Gaya is a modern love dilemma where love, truth, and betrayal clash.\n<br/><br/>\nKaushal's perfect world breaks, Tina struggles with silent emotions, and Veer loves openly and honestly. \n<br/><br/>\nThree hearts face guilt, desire, and tough choices in an emotional journey of broken trust, acceptance, and forgiveness.\n","g":["Drama","Romantic"],"l":["Hindi"],"rt":113,"ct":"UA16+","days":[{"d":1,"dt":20260306,"n":0.02},{"d":3,"dt":20260308,"n":0.03},{"d":4,"dt":20260309,"n":0.03},{"d":5,"dt":20260310,"n":0.02},{"d":6,"dt":20260311,"n":0.02},{"d":7,"dt":20260312,"n":0.02},{"d":8,"dt":20260313,"n":0.01},{"d":9,"dt":20260314,"n":0.02},{"d":10,"dt":20260315,"n":0.02}],"tn":0.19,"d1os":0,"d2os":0,"d3os":0,"d4os":0,"wos":0,"tos":0,"vd":""}